avro_compat/__init__.py
avro_compat/avro/__init__.py
avro_compat/avro/__main__.py
avro_compat/avro/codecs.py
avro_compat/avro/compatibility.py
avro_compat/avro/constants.py
avro_compat/avro/datafile.py
avro_compat/avro/errors.py
avro_compat/avro/io.py
avro_compat/avro/protocol.py
avro_compat/avro/schema.py
avro_compat/avro/schemanormalization.py
avro_compat/avro/timezones.py
avro_compat/avro/utils.py
avro_compat/fastavro/__init__.py
avro_compat/fastavro/__main__.py
avro_compat/fastavro/_logical_readers.py
avro_compat/fastavro/_logical_writers.py
avro_compat/fastavro/_logical_writers_py.py
avro_compat/fastavro/_read.py
avro_compat/fastavro/_read_common.py
avro_compat/fastavro/_read_py.py
avro_compat/fastavro/_schema_common.py
avro_compat/fastavro/_write.py
avro_compat/fastavro/const.py
avro_compat/fastavro/read.py
avro_compat/fastavro/schema.py
avro_compat/fastavro/utils.py
avro_compat/fastavro/validation.py
avro_compat/fastavro/write.py
avro_compat/fastavro/io/binary_decoder.py
avro_compat/fastavro/io/json_decoder.py
avro_compat/fastavro/io/json_encoder.py
avro_compat/fastavro/io/symbols.py
avro_compat/fastavro/repository/__init__.py
avro_compat/fastavro/repository/base.py
avro_compat/fastavro/repository/flat_dict.py
avro_compat-0.0.3.dist-info/LICENSE
avro_compat-0.0.3.dist-info/WHEEL
avro_compat-0.0.3.dist-info/METADATA
avro_compat-0.0.3.dist-info/RECORD
