Metadata-Version: 2.1
Name: avro-compat
Version: 0.0.3
Summary: A library-compatibility layer for avro parsers
Author-email: Steve Stagg <stestagg@gmail.com>
Requires-Python: >=3.8
Classifier: Development Status :: 3 - Alpha
Classifier: Intended Audience :: Developers
Classifier: License :: OSI Approved :: BSD License
Classifier: Programming Language :: Python :: 3 :: Only
Classifier: Programming Language :: Python :: 3.8
Classifier: Programming Language :: Python :: 3.9
Classifier: Programming Language :: Python :: 3.10
Requires-Dist: avro
Requires-Dist: fastavro
Requires-Dist: bandit[toml]==1.7.5 ; extra == "test"
Requires-Dist: black==23.9.1 ; extra == "test"
Requires-Dist: check-manifest==0.49 ; extra == "test"
Requires-Dist: flake8-bugbear==23.9.16 ; extra == "test"
Requires-Dist: flake8-docstrings ; extra == "test"
Requires-Dist: flake8==6.1.0 ; extra == "test"
Requires-Dist: pre-commit==3.4.0 ; extra == "test"
Requires-Dist: pylint==3.0.1 ; extra == "test"
Requires-Dist: pylint_junit ; extra == "test"
Requires-Dist: pytest-mock<3.11.2 ; extra == "test"
Requires-Dist: pytest-cov==4.1.0 ; extra == "test"
Requires-Dist: pytest-runner ; extra == "test"
Requires-Dist: pytest==7.4.2 ; extra == "test"
Requires-Dist: shellcheck-py==0.9.0.6 ; extra == "test"
Project-URL: Documentation, https://github.com/microsoft/python-package-template/tree/main#readme
Project-URL: Source, https://github.com/microsoft/python-package-template
Project-URL: Tracker, https://github.com/microsoft/python-package-template/issues
Provides-Extra: test
